{
  "title": "A Trip to Paradise",
  "year": "1921",
  "rated": "N/A",
  "released": "05 Sep 1921",
  "runtime": "N/A",
  "genre": "Drama",
  "director": "Maxwell Karger",
  "writer": "Benjamin Glazer, June Mathis, Ferenc Molnár",
  "actors": "Bert Lytell, Virginia Valli, Brinsley Shaw",
  "plot": "A somewhat disguised silent version of Molnar's \"Liliom\", released the same year that Molnar's play first opened on Broadway.",
  "language": "None, English",
  "country": "United States",
  "awards": "N/A",
  "poster": "https://m.media-amazon.com/images/M/MV5BYzJkOGM0ZjQtODc0YS00NTcyLTkzZjEtNDNjZjQ5M2JjMDlmXkEyXkFqcGdeQXVyMTcyODY2NDQ@._V1_SX300.jpg",
  "ratings": [],
  "metascore": "N/A",
  "imdbRating": "N/A",
  "imdbID": "tt0012779",
  "type": "movie",
  "fetched_at": "2026-03-10T13:30:32.688Z"
}