{
  "title": "Court-Martial",
  "year": "1928",
  "rated": "Passed",
  "released": "12 Aug 1928",
  "runtime": "65 min",
  "genre": "Action, Adventure, Drama",
  "director": "George B. Seitz",
  "writer": "Elmer Harris, Anthony Coldeway, Mort Blumenstock",
  "actors": "Jack Holt, Betty Compson, Pat Harmon",
  "plot": "During the American Civil War, A Union-Army officer is ordered by U. S. President Abraham Lincoln to bring in Belle Starr, the leader of a Missouri guerrilla band, dead or alive. However, he falls in love with her, does not bring ...",
  "language": "None",
  "country": "United States",
  "awards": "N/A",
  "poster": "https://m.media-amazon.com/images/M/MV5BNmJmNTZlZTQtN2UxNy00MmU4LWEyMzItM2M0ZTdkMjc1MDRlXkEyXkFqcGdeQXVyMjUxODE0MDY@._V1_SX300.jpg",
  "ratings": [
    {
      "Source": "Internet Movie Database",
      "Value": "6.6/10"
    }
  ],
  "metascore": "N/A",
  "imdbRating": "6.6",
  "imdbID": "tt0018797",
  "type": "movie",
  "fetched_at": "2026-03-16T15:23:47.620Z"
}