{
  "title": "Dollars for a Fast Gun",
  "year": "1966",
  "rated": "N/A",
  "released": "10 Mar 1966",
  "runtime": "99 min",
  "genre": "Comedy, Western",
  "director": "Joaquín Luis Romero Marchent",
  "writer": "Sergio Donati, Joaquín Luis Romero Marchent",
  "actors": "Robert Hundar, Pamela Tudor, Luigi Pistilli",
  "plot": "In a desert region, Martin, bound to a wheelchair, is served by a gang of bandits to collect rents and kill anybody who resists. Then Lassiter arrives, telling Martin that he knows where Frank is, the man who made him a cripple.",
  "language": "Italian",
  "country": "Italy, Spain",
  "awards": "N/A",
  "poster": "https://m.media-amazon.com/images/M/MV5BNzc4MTY1NmEtMTk4MC00ZTIzLTlhMzctYzVhNGNlNzdkYjlhXkEyXkFqcGc@._V1_SX300.jpg",
  "ratings": [
    {
      "Source": "Internet Movie Database",
      "Value": "5.8/10"
    }
  ],
  "metascore": "N/A",
  "imdbRating": "5.8",
  "imdbID": "tt0060225",
  "type": "movie",
  "fetched_at": "2026-06-07T18:42:22.954Z"
}