{
  "title": "Eadie Was a Lady",
  "year": "1945",
  "rated": "Passed",
  "released": "23 Jan 1945",
  "runtime": "67 min",
  "genre": "Comedy, Music, Romance",
  "director": "Arthur Dreifuss",
  "writer": "Monte Brice",
  "actors": "Ann Miller, Joe Besser, William Wright",
  "plot": "Edithea Alden, a college girl from a wealthy family, is working at night as dancer in a nightclub. When the leading lady Rose is loosing the customers attractiong, Editha gets her job, but due to the fact that her double life coul...",
  "language": "English",
  "country": "United States",
  "awards": "N/A",
  "poster": "https://m.media-amazon.com/images/M/MV5BMDg1NjE1YmQtMDE1NS00ZmIyLWEwOTUtOTQ4MjJjYmI5Y2NiXkEyXkFqcGdeQXVyMTY5Nzc4MDY@._V1_SX300.jpg",
  "ratings": [
    {
      "Source": "Internet Movie Database",
      "Value": "6.5/10"
    }
  ],
  "metascore": "N/A",
  "imdbRating": "6.5",
  "imdbID": "tt0037663",
  "type": "movie",
  "fetched_at": "2026-04-17T18:00:25.269Z"
}