{
  "title": "El rufián",
  "year": "1961",
  "rated": "N/A",
  "released": "07 Sep 1961",
  "runtime": "120 min",
  "genre": "Drama, Thriller",
  "director": "Daniel Tinayre",
  "writer": "Eduardo Borrás, Daniel Tinayre",
  "actors": "Carlos Estrada, Egle Martin, Óscar Rovito",
  "plot": "An amnesiac carnival psychic is haunted by the thought that a man is coming to kill her.",
  "language": "Spanish",
  "country": "Argentina",
  "awards": "N/A",
  "poster": "https://m.media-amazon.com/images/M/MV5BYmExNjk0NWMtZDg1NS00MWRkLTkwZWQtNTVkZmZmNTVkZTAzXkEyXkFqcGc@._V1_SX300.jpg",
  "ratings": [
    {
      "Source": "Internet Movie Database",
      "Value": "7.1/10"
    }
  ],
  "metascore": "N/A",
  "imdbRating": "7.1",
  "imdbID": "tt0054254",
  "type": "movie",
  "fetched_at": "2026-05-29T19:37:40.740Z"
}