{
  "title": "Feudin' Rhythm",
  "year": "1949",
  "rated": "Approved",
  "released": "03 Nov 1949",
  "runtime": "65 min",
  "genre": "Comedy, Music, Western",
  "director": "Edward Bernds",
  "writer": "Barry Shipman",
  "actors": "Eddy Arnold, Gloria Henry, Kirby Grant",
  "plot": "Eddy Arnold (Eddy Arnold), singing star of the Ace Lucky (Kirby Grant) radio program gets involved when Ace's equipment for a television program is destroyed by a fire. Aces accepts the sponsorship of social-climber Lucille Upperw...",
  "language": "English",
  "country": "United States",
  "awards": "N/A",
  "poster": "https://m.media-amazon.com/images/M/MV5BMzgwZWY1ZjMtMjViZi00ZmNlLTllYWItZmQxNTlkNTA3ZDc0XkEyXkFqcGdeQXVyNDA3OTk2OTY@._V1_SX300.jpg",
  "ratings": [
    {
      "Source": "Internet Movie Database",
      "Value": "5.5/10"
    }
  ],
  "metascore": "N/A",
  "imdbRating": "5.5",
  "imdbID": "tt0041355",
  "type": "movie",
  "fetched_at": "2026-05-02T18:43:38.130Z"
}