{
  "title": "Fight for Your Lady",
  "year": "1937",
  "rated": "Passed",
  "released": "05 Nov 1937",
  "runtime": "66 min",
  "genre": "Comedy, Romance",
  "director": "Benjamin Stoloff",
  "writer": "Ernest Pagano, Harry Segall, Harold Daniel Kusel",
  "actors": "John Boles, Jack Oakie, Ida Lupino",
  "plot": "Wrestling trainer puts himself in charge of a singer's love life when the singer is jilted by a rich girl.",
  "language": "English",
  "country": "United States",
  "awards": "N/A",
  "poster": "https://m.media-amazon.com/images/M/MV5BMWNkNDNkZGEtODdjMi00MzZhLTgwNjAtNzdhMzUzNTFhZDQ4XkEyXkFqcGdeQXVyNTUyNzA5ODE@._V1_SX300.jpg",
  "ratings": [
    {
      "Source": "Internet Movie Database",
      "Value": "5.4/10"
    }
  ],
  "metascore": "N/A",
  "imdbRating": "5.4",
  "imdbID": "tt0028868",
  "type": "movie",
  "fetched_at": "2026-04-06T21:01:21.489Z"
}