{
  "title": "Holiday in Bombay",
  "year": "1963",
  "rated": "N/A",
  "released": "N/A",
  "runtime": "N/A",
  "genre": "Drama",
  "director": "P.L. Santoshi",
  "writer": "Madhusudan Kalelkar, Mahendra Saral",
  "actors": "Shashi Kapoor, Vijaya Choudhury, Rajendranath Malhotra",
  "plot": "Cousins and avowed bachelors, Nath and Gautam, plan a trip to Bombay with the sole motto of entertainment, fun and frolic. After drinking the cup of pleasure to its full they should return to their native place as neat and clean a...",
  "language": "Hindi",
  "country": "India",
  "awards": "N/A",
  "poster": "https://m.media-amazon.com/images/M/MV5BN2QzODA3YzUtYThiZS00MWE5LTgzZjAtNWY4Mjk0OTQ3NTUxXkEyXkFqcGc@._V1_SX300.jpg",
  "ratings": [
    {
      "Source": "Internet Movie Database",
      "Value": "5.7/10"
    }
  ],
  "metascore": "N/A",
  "imdbRating": "5.7",
  "imdbID": "tt0269331",
  "type": "movie",
  "fetched_at": "2026-06-02T16:39:14.818Z"
}