{
  "title": "If I Were Queen",
  "year": "1922",
  "rated": "N/A",
  "released": "15 Oct 1922",
  "runtime": "N/A",
  "genre": "Drama, Romance",
  "director": "Wesley Ruggles",
  "writer": "Du Vernet Rabell, Carol Warren",
  "actors": "Ethel Clayton, Andrée Lejon, Warner Baxter",
  "plot": "Ruth Townley, an American heiress, drops a locket received from her friend, Princess Oluf of Kosnia. It is retrieved by Prince Valdemir of Prebilof, who assumes its owner to be Oluf and falls in love with her. Ruth and Valdemir ar...",
  "language": "None",
  "country": "United States",
  "awards": "N/A",
  "poster": "https://m.media-amazon.com/images/M/MV5BODAxY2E5ZjctNzI0Ny00NDgyLWEwYTMtYjcxZjJkNDQ5OTEzXkEyXkFqcGdeQXVyNjA5MTAzODY@._V1_SX300.jpg",
  "ratings": [],
  "metascore": "N/A",
  "imdbRating": "N/A",
  "imdbID": "tt0013261",
  "type": "movie",
  "fetched_at": "2026-03-10T13:37:27.144Z"
}