{
  "title": "In Caliente",
  "year": "1935",
  "rated": "Approved",
  "released": "25 May 1935",
  "runtime": "84 min",
  "genre": "Comedy, Musical, Romance",
  "director": "Lloyd Bacon",
  "writer": "Jerry Wald, Julius J. Epstein, Ralph Block",
  "actors": "Dolores Del Río, Pat O'Brien, Leo Carrillo",
  "plot": "A magazine editor at a resort falls for a Spanish dancer he once criticized, unaware of her identity. Her uncle plots to exploit this, while she seeks revenge. A rival pursues the editor as romance blooms.",
  "language": "English, Spanish",
  "country": "United States",
  "awards": "2 wins total",
  "poster": "https://m.media-amazon.com/images/M/MV5BNjQzZmQ0MzctOTg0Ny00OGFjLWEwMGUtMTdhNjcwODY2OWI5XkEyXkFqcGc@._V1_SX300.jpg",
  "ratings": [
    {
      "Source": "Internet Movie Database",
      "Value": "5.9/10"
    }
  ],
  "metascore": "N/A",
  "imdbRating": "5.9",
  "imdbID": "tt0026523",
  "type": "movie",
  "fetched_at": "2026-04-05T16:52:34.273Z"
}