{
  "title": "È l'amor che mi rovina",
  "year": "1951",
  "rated": "N/A",
  "released": "04 Mar 1955",
  "runtime": "101 min",
  "genre": "Comedy, Crime",
  "director": "Mario Soldati",
  "writer": "Enrico Blasi, Mario Monicelli, Steno",
  "actors": "Walter Chiari, Lucia Bosè, Aroldo Tieri",
  "plot": "The young Walter, anything but sporty, falls in love with Clara, a ski instructor.",
  "language": "Italian",
  "country": "Italy",
  "awards": "N/A",
  "poster": "https://m.media-amazon.com/images/M/MV5BOTQ0MDhkYWYtY2MwMy00NjA0LTgzODYtMjQzYThkOTQ5MzNlXkEyXkFqcGc@._V1_SX300.jpg",
  "ratings": [
    {
      "Source": "Internet Movie Database",
      "Value": "5.1/10"
    }
  ],
  "metascore": "N/A",
  "imdbRating": "5.1",
  "imdbID": "tt0044226",
  "type": "movie",
  "fetched_at": "2026-05-06T22:29:10.314Z"
}