{
  "title": "Man on the Tracks",
  "year": "1957",
  "rated": "N/A",
  "released": "17 Jan 1957",
  "runtime": "89 min",
  "genre": "Drama",
  "director": "Andrzej Munk",
  "writer": "Andrzej Munk, Jerzy Stefan Stawinski",
  "actors": "Kazimierz Opalinski, Zygmunt Maciejewski, Zygmunt Zintel",
  "plot": "In 1950, at night, a passenger train kills a man on the tracks. He is Orzechowski, an engineer since 1914. An inquiry immediately follows. Testimony takes the form of flashbacks. Tuszka, the station master, believes Orzechowski wa...",
  "language": "Polish",
  "country": "Poland",
  "awards": "1 win & 1 nomination",
  "poster": "https://m.media-amazon.com/images/M/MV5BNjRjODZjNTYtOTJkYS00ZjY3LWJmMzMtNDYyMDJkOTY1OGRjXkEyXkFqcGdeQXVyNzQ1NDIxMDQ@._V1_SX300.jpg",
  "ratings": [
    {
      "Source": "Internet Movie Database",
      "Value": "7.6/10"
    }
  ],
  "metascore": "N/A",
  "imdbRating": "7.6",
  "imdbID": "tt0050282",
  "type": "movie",
  "fetched_at": "2026-05-20T13:58:15.829Z"
}