{
  "title": "Moon Over Las Vegas",
  "year": "1944",
  "rated": "Approved",
  "released": "01 Apr 1944",
  "runtime": "65 min",
  "genre": "Comedy, Music, Romance",
  "director": "Jean Yarbrough",
  "writer": "George Jeske, Clyde Bruckman",
  "actors": "Anne Gwynne, David Bruce, Barbara Jo Allen",
  "plot": "A beautiful woman goes to Las Vegas in a scheme to make her husbnd jealous, but once she gets there she becomes involved with another man.",
  "language": "English",
  "country": "United States",
  "awards": "N/A",
  "poster": "https://m.media-amazon.com/images/M/MV5BMGE0ZDY3MzUtOTE5OS00N2FiLTk4M2QtZTE5NjhkNDI0MjZjXkEyXkFqcGdeQXVyMzc5ODc1MDY@._V1_SX300.jpg",
  "ratings": [
    {
      "Source": "Internet Movie Database",
      "Value": "6.4/10"
    }
  ],
  "metascore": "N/A",
  "imdbRating": "6.4",
  "imdbID": "tt0037085",
  "type": "movie",
  "fetched_at": "2026-04-15T14:39:59.628Z"
}