{
  "title": "Not a Love Story: Making (500) Days of Summer",
  "year": "2009",
  "rated": "Not Rated",
  "released": "22 Dec 2009",
  "runtime": "30 min",
  "genre": "Documentary, Short",
  "director": "Charles de Lauzirika",
  "writer": "N/A",
  "actors": "Zooey Deschanel, Joseph Gordon-Levitt, Scott Neustadter, Marc Webb",
  "plot": "A behind-the-scenes documentary exploring the making of Marc Webb's 500 Days of Summer (2009).",
  "language": "English",
  "country": "USA",
  "awards": "N/A",
  "poster": "N/A",
  "ratings": [
    {
      "Source": "Internet Movie Database",
      "Value": "7.7/10"
    }
  ],
  "metascore": "N/A",
  "imdbRating": "7.7",
  "imdbID": "tt1572162",
  "type": "movie",
  "fetched_at": "2026-02-18T21:57:15.128Z"
}