{
  "title": "...och efter skymning kommer mörker",
  "year": "1947",
  "rated": "N/A",
  "released": "05 Apr 1947",
  "runtime": "85 min",
  "genre": "Crime, Drama, Horror",
  "director": "Rune Hagberg",
  "writer": "Rune Hagberg",
  "actors": "Rune Hagberg, Ami Aaröe, John Wilhelm Hagberg",
  "plot": "A man end up in a spiritual crisis when he discover a genetic mental disease in the family history.",
  "language": "Swedish",
  "country": "Sweden",
  "awards": "N/A",
  "poster": "https://m.media-amazon.com/images/M/MV5BNTgyZjhhYTktODM0Ny00NDA4LTlhZmMtN2FjZWJlOTgyYzdhXkEyXkFqcGc@._V1_SX300.jpg",
  "ratings": [
    {
      "Source": "Internet Movie Database",
      "Value": "5.7/10"
    }
  ],
  "metascore": "N/A",
  "imdbRating": "5.7",
  "imdbID": "tt0039126",
  "type": "movie",
  "fetched_at": "2026-04-23T14:43:27.283Z"
}