{
  "title": "Odds 777",
  "year": "1932",
  "rated": "N/A",
  "released": "04 Nov 1932",
  "runtime": "91 min",
  "genre": "Comedy, Family, Musical",
  "director": "George Schnéevoigt",
  "writer": "Fleming Lynge, Paul Sarauw",
  "actors": "Liva Weel, Emanuel Gregers, Inger Stender",
  "plot": "Since the kitchen girl Hansy by mistake wins a handsome sum of money on the trotting track, she will use it with manners. She stays at a fashionable beach hotel as a consul and meets landowner, widower and horse owner Rosen. The a...",
  "language": "Danish",
  "country": "Denmark",
  "awards": "N/A",
  "poster": "https://m.media-amazon.com/images/M/MV5BYWE1OTBiOWEtMGUyZi00NTljLWEyMDEtYTg3NjllMjAyMDI0XkEyXkFqcGc@._V1_SX300.jpg",
  "ratings": [
    {
      "Source": "Internet Movie Database",
      "Value": "6.9/10"
    }
  ],
  "metascore": "N/A",
  "imdbRating": "6.9",
  "imdbID": "tt0122639",
  "type": "movie",
  "fetched_at": "2026-04-02T18:45:19.603Z"
}