{
  "title": "Pride of the West",
  "year": "1938",
  "rated": "Approved",
  "released": "08 Jul 1938",
  "runtime": "56 min",
  "genre": "Drama, Western",
  "director": "Lesley Selander",
  "writer": "Nate Watt, Clarence E. Mulford",
  "actors": "William Boyd, George 'Gabby' Hayes, Russell Hayden",
  "plot": "Cattle rustlers rob a stagecoach, leaving the sheriff in a tight spot. His daughter seeks help from a resourceful cowboy, who recovers the stolen money and masterminds a trap to capture the outlaws.",
  "language": "English",
  "country": "United States",
  "awards": "N/A",
  "poster": "https://m.media-amazon.com/images/M/MV5BNjNiY2RkYzctNWRkMS00NTQ2LWJlOTEtYzZiYzNmZGVkZjRkXkEyXkFqcGc@._V1_SX300.jpg",
  "ratings": [
    {
      "Source": "Internet Movie Database",
      "Value": "6.2/10"
    }
  ],
  "metascore": "N/A",
  "imdbRating": "6.2",
  "imdbID": "tt0030621",
  "type": "movie",
  "fetched_at": "2026-04-07T13:38:10.590Z"
}