{
  "title": "Quadrille",
  "year": "1938",
  "rated": "N/A",
  "released": "N/A",
  "runtime": "95 min",
  "genre": "Comedy, Romance",
  "director": "Sacha Guitry",
  "writer": "Sacha Guitry",
  "actors": "Sacha Guitry, Gaby Morlay, Jacqueline Delubac",
  "plot": "The battle of the sexes as drawing room social satire. Philippe, a middle-aged newspaper editor, has lived for six years with Paulette, a successful stage actress. He tells her friend Claudine, a realistic and enterprising reporte...",
  "language": "French",
  "country": "France",
  "awards": "N/A",
  "poster": "https://m.media-amazon.com/images/M/MV5BYzFkNDc0YmQtZGFiNC00YzhiLTgxNDItZjliNzVlYjc5MGE0XkEyXkFqcGdeQXVyMzg1ODEwNQ@@._V1_SX300.jpg",
  "ratings": [
    {
      "Source": "Internet Movie Database",
      "Value": "6.7/10"
    }
  ],
  "metascore": "N/A",
  "imdbRating": "6.7",
  "imdbID": "tt0030642",
  "type": "movie",
  "fetched_at": "2026-04-07T13:37:37.539Z"
}