{
  "title": "Sant Dnyaneshwar",
  "year": "1940",
  "rated": "N/A",
  "released": "18 May 1940",
  "runtime": "139 min",
  "genre": "Biography, Drama, Fantasy",
  "director": "Vishnupant Govind Damle, Sheikh Fattelal",
  "writer": "Shivram Vashikar",
  "actors": "Shahu Modak, Datta Dharmadhikari, Pandit",
  "plot": "Story of a boy who finds enlightenment by experiencing religious hypocrisy and dogmatism. Dnyaneshwar liberated the \"divine knowledge\" locked in the Sanskrit language to bring that knowledge into Prakrit (Marathi) and made it avai...",
  "language": "Hindi, Marathi",
  "country": "India",
  "awards": "N/A",
  "poster": "https://m.media-amazon.com/images/M/MV5BOGYwMTc1MDUtYTBiYi00MTE3LWIxNTMtYjY3OGU4MmIyMDFiXkEyXkFqcGc@._V1_SX300.jpg",
  "ratings": [
    {
      "Source": "Internet Movie Database",
      "Value": "7.8/10"
    }
  ],
  "metascore": "N/A",
  "imdbRating": "7.8",
  "imdbID": "tt0158914",
  "type": "movie",
  "fetched_at": "2026-04-09T17:43:00.496Z"
}