{
  "title": "Social Register",
  "year": "1934",
  "rated": "Passed",
  "released": "10 Mar 1934",
  "runtime": "71 min",
  "genre": "Comedy, Drama, Music",
  "director": "Marshall Neilan",
  "writer": "John Emerson, Anita Loos, Clara Beranger",
  "actors": "Colleen Moore, Charles Winninger, Pauline Frederick",
  "plot": "Chorus-girl Patsy Shaw crashes a high-society party and meets playboy Charlie Breen; they fall in love and are soon on their merry way to wedded bliss. However, Charlie's snobbish mother does not think that Patsy is worthy of her ...",
  "language": "English",
  "country": "United States",
  "awards": "N/A",
  "poster": "https://m.media-amazon.com/images/M/MV5BYTg4YWM0OTMtMjk4My00Mjk1LTg3YWYtZmE2NDgzMjY4MDk3XkEyXkFqcGc@._V1_SX300.jpg",
  "ratings": [
    {
      "Source": "Internet Movie Database",
      "Value": "6.8/10"
    }
  ],
  "metascore": "N/A",
  "imdbRating": "6.8",
  "imdbID": "tt0025806",
  "type": "movie",
  "fetched_at": "2026-04-03T23:37:54.707Z"
}