{
  "title": "Sons of the Desert",
  "year": "1933",
  "rated": "Passed",
  "released": "29 Dec 1933",
  "runtime": "68 min",
  "genre": "Comedy, Family",
  "director": "William A. Seiter",
  "writer": "Frank Craven, Oliver Hardy, Jack Barty",
  "actors": "Stan Laurel, Oliver Hardy, Charley Chase",
  "plot": "When Stan and Ollie trick their wives into thinking that they are taking a medicinal cruise while they're actually going to a convention, the wives find out the truth the hard way.",
  "language": "English",
  "country": "United States",
  "awards": "1 win total",
  "poster": "https://m.media-amazon.com/images/M/MV5BZjIyNDJkMTktYWU0OC00OGE2LWFjM2MtODU1ZTM3YzhkMzQyXkEyXkFqcGc@._V1_SX300.jpg",
  "ratings": [
    {
      "Source": "Internet Movie Database",
      "Value": "7.5/10"
    },
    {
      "Source": "Rotten Tomatoes",
      "Value": "100%"
    }
  ],
  "metascore": "N/A",
  "imdbRating": "7.5",
  "imdbID": "tt0024601",
  "type": "movie",
  "fetched_at": "2026-04-03T23:22:37.211Z"
}