{
  "title": "Tamahine",
  "year": "1963",
  "rated": "N/A",
  "released": "03 May 1964",
  "runtime": "95 min",
  "genre": "Comedy, Sport",
  "director": "Philip Leacock",
  "writer": "Denis Cannan, Thelma Niklaus",
  "actors": "Nancy Kwan, John Fraser, Dennis Price",
  "plot": "A free-spirited young Polynesian girl is sent to live with her uncle in England. The many social and other rules new to her that she encounters there, as well as attention from student body of a local school cause much hilarity.",
  "language": "English",
  "country": "United Kingdom",
  "awards": "Nominated for 1 BAFTA Award1 nomination total",
  "poster": "https://m.media-amazon.com/images/M/MV5BMTMxYmY1MTUtNWQ1Zi00Y2RmLWE2MDEtOTUxZDIyMWE4ODEzL2ltYWdlXkEyXkFqcGdeQXVyMjU5OTg5NDc@._V1_SX300.jpg",
  "ratings": [
    {
      "Source": "Internet Movie Database",
      "Value": "5.9/10"
    }
  ],
  "metascore": "N/A",
  "imdbRating": "5.9",
  "imdbID": "tt0058636",
  "type": "movie",
  "fetched_at": "2026-06-02T15:31:07.561Z"
}