{
  "title": "The Neanderthal Man",
  "year": "1953",
  "rated": "Not Rated",
  "released": "19 Jun 1953",
  "runtime": "78 min",
  "genre": "Horror, Sci-Fi",
  "director": "Ewald André Dupont",
  "writer": "Aubrey Wisberg, Jack Pollexfen",
  "actors": "Robert Shayne, Joyce Terry, Richard Crane",
  "plot": "Professor Groves, an expert in prehistoric life, proves his theories with an extract that'll regress a cat to a saber-tooth tiger and man to a Neanderthal.",
  "language": "English, American Sign ",
  "country": "United States",
  "awards": "N/A",
  "poster": "https://m.media-amazon.com/images/M/MV5BNTFlYWZjMTQtZTUzOC00OWJkLWJlYTEtMTI0YTRlYzE4Y2VjXkEyXkFqcGc@._V1_SX300.jpg",
  "ratings": [
    {
      "Source": "Internet Movie Database",
      "Value": "4.4/10"
    }
  ],
  "metascore": "N/A",
  "imdbRating": "4.4",
  "imdbID": "tt0046121",
  "type": "movie",
  "fetched_at": "2026-05-15T21:11:25.248Z"
}