{
  "title": "The Rawhide Years",
  "year": "1956",
  "rated": "Approved",
  "released": "01 Jul 1956",
  "runtime": "85 min",
  "genre": "Western",
  "director": "Rudolph Maté",
  "writer": "Earl Felton, Robert Presnell Jr., D.D. Beauchamp",
  "actors": "Tony Curtis, Colleen Miller, Arthur Kennedy",
  "plot": "Dishonest riverboat gambler Ben Matthews is blamed for a murder he didn't commit and must find the real killer before the lynch mob finds him.",
  "language": "English",
  "country": "United States",
  "awards": "N/A",
  "poster": "https://m.media-amazon.com/images/M/MV5BODJlMmIxMmQtNjBlOS00NTdhLWFjODAtNjhmYWZiMTQ3ZWIxXkEyXkFqcGc@._V1_SX300.jpg",
  "ratings": [
    {
      "Source": "Internet Movie Database",
      "Value": "6.1/10"
    }
  ],
  "metascore": "N/A",
  "imdbRating": "6.1",
  "imdbID": "tt0049663",
  "type": "movie",
  "fetched_at": "2026-05-20T03:33:00.762Z"
}