{
  "title": "The Hundred Pound Window",
  "year": "1944",
  "rated": "N/A",
  "released": "03 Apr 1944",
  "runtime": "84 min",
  "genre": "Crime, Drama, Thriller",
  "director": "Brian Desmond Hurst",
  "writer": "Rodney Ackland, Abem Finkel, Mark Hellinger",
  "actors": "Anne Crawford, David Farrar, Frederick Leister",
  "plot": "An accountant is forced by circumstances to take a job at the racetrack. He is working at the betting window when he is drawn into a gang of criminals and their illegal schemes.",
  "language": "English",
  "country": "United Kingdom",
  "awards": "N/A",
  "poster": "N/A",
  "ratings": [
    {
      "Source": "Internet Movie Database",
      "Value": "5.9/10"
    }
  ],
  "metascore": "N/A",
  "imdbRating": "5.9",
  "imdbID": "tt0036935",
  "type": "movie",
  "fetched_at": "2026-04-16T15:42:59.426Z"
}