{
  "title": "The Indian Scarf",
  "year": "1963",
  "rated": "N/A",
  "released": "13 Sep 1963",
  "runtime": "93 min",
  "genre": "Crime, Drama, Mystery",
  "director": "Alfred Vohrer",
  "writer": "Edgar Wallace, Harald G. Petersson, Georg Hurdalek",
  "actors": "Heinz Drache, Corny Collins, Klaus Kinski",
  "plot": "When a wealthy man dies, his relatives look forward to inheriting all his money. He leaves a provision in his will that they all must spend a week together in his castle. At the castle, the relatives soon begin to be killed off on...",
  "language": "German",
  "country": "West Germany",
  "awards": "N/A",
  "poster": "https://m.media-amazon.com/images/M/MV5BZWVlNDUwMGItYWM1Mi00ZDNmLThmNWMtOTY3Nzg5MmI0ZjI0XkEyXkFqcGc@._V1_SX300.jpg",
  "ratings": [
    {
      "Source": "Internet Movie Database",
      "Value": "6.6/10"
    }
  ],
  "metascore": "N/A",
  "imdbRating": "6.6",
  "imdbID": "tt0057183",
  "type": "movie",
  "fetched_at": "2026-06-02T15:28:52.970Z"
}