{
  "title": "The Punch Bowl",
  "year": "1944",
  "rated": "N/A",
  "released": "07 Apr 1944",
  "runtime": "97 min",
  "genre": "Comedy, Family",
  "director": "Helmut Weiss",
  "writer": "Heinrich Spoerl",
  "actors": "Heinz Rühmann, Karin Himboldt, Hilde Sessak",
  "plot": "A successful writer, home-schooled in his youth, masquerades as a student at a secondary school to experience all the fun and pranks he missed out on.",
  "language": "German",
  "country": "Germany",
  "awards": "N/A",
  "poster": "https://m.media-amazon.com/images/M/MV5BNjFmMDllYzMtMTRiOC00MGUxLWI5NzItYmRjMzY4ZWM3ZGMwXkEyXkFqcGc@._V1_SX300.jpg",
  "ratings": [
    {
      "Source": "Internet Movie Database",
      "Value": "7.7/10"
    }
  ],
  "metascore": "N/A",
  "imdbRating": "7.7",
  "imdbID": "tt0036818",
  "type": "movie",
  "fetched_at": "2026-04-15T14:34:20.213Z"
}