{
  "title": "The Perfect Crime",
  "year": "1928",
  "rated": "N/A",
  "released": "04 Aug 1928",
  "runtime": "83 min",
  "genre": "Crime, Drama",
  "director": "Bert Glennon",
  "writer": "Ewart Adamson, Randolph Bartlett, Victor Currier",
  "actors": "Clive Brook, Irene Rich, Ethel Wales",
  "plot": "A police inspector \"solves\" a crime that, in fact, might not have occurred at all.",
  "language": "English",
  "country": "United States",
  "awards": "N/A",
  "poster": "https://m.media-amazon.com/images/M/MV5BMTczMTY3NjgyNl5BMl5BanBnXkFtZTgwNDk0ODY1MjE@._V1_SX300.jpg",
  "ratings": [
    {
      "Source": "Internet Movie Database",
      "Value": "4.8/10"
    }
  ],
  "metascore": "N/A",
  "imdbRating": "4.8",
  "imdbID": "tt0019264",
  "type": "movie",
  "fetched_at": "2026-03-16T15:23:59.227Z"
}