{
  "title": "The Legend of Blood Mountain",
  "year": "1965",
  "rated": "N/A",
  "released": "29 Sep 1965",
  "runtime": "76 min",
  "genre": "Comedy, Crime, Drama",
  "director": "Massey Cramer",
  "writer": "Bob Corley",
  "actors": "George Ellis, Erin Fleming, Edward Yastin",
  "plot": "A small-town newspaperman begins to suspect that a wave of murders committed in the area may not be the work of a serial killer but a monster.",
  "language": "English",
  "country": "United States",
  "awards": "N/A",
  "poster": "https://m.media-amazon.com/images/M/MV5BZDlhMTgyOWUtYjA0Zi00YWIyLWExYzktMDczY2U5ZjcxOTRmXkEyXkFqcGdeQXVyMjQ0ODE4OTU@._V1_SX300.jpg",
  "ratings": [
    {
      "Source": "Internet Movie Database",
      "Value": "3.2/10"
    }
  ],
  "metascore": "N/A",
  "imdbRating": "3.2",
  "imdbID": "tt0229528",
  "type": "movie",
  "fetched_at": "2026-06-05T18:24:38.360Z"
}