{
  "title": "Three in the Saddle",
  "year": "1945",
  "rated": "Passed",
  "released": "26 Jul 1945",
  "runtime": "61 min",
  "genre": "Western",
  "director": "Harry L. Fraser",
  "writer": "Elmer Clifton",
  "actors": "Tex Ritter, Dave O'Brien, Guy Wilkerson",
  "plot": "Rankin and Manning and their outlaw gang are after Barlow's Tin Cup Ranch. Rangers Wyatt and Perkins arrive to help legally but Haines wants to take the law into his own hands.",
  "language": "English",
  "country": "United States",
  "awards": "N/A",
  "poster": "https://m.media-amazon.com/images/M/MV5BMjdmOWNkZTAtOThjYi00ZjU5LWIxODUtMGYzODIxNjljN2U3XkEyXkFqcGdeQXVyMTY5Nzc4MDY@._V1_SX300.jpg",
  "ratings": [
    {
      "Source": "Internet Movie Database",
      "Value": "6.7/10"
    }
  ],
  "metascore": "N/A",
  "imdbRating": "6.7",
  "imdbID": "tt0038168",
  "type": "movie",
  "fetched_at": "2026-04-17T18:02:45.950Z"
}