{
  "title": "To Hell with the Virtue",
  "year": "1953",
  "rated": "N/A",
  "released": "03 May 1953",
  "runtime": "90 min",
  "genre": "Comedy",
  "director": "Jean Laviron",
  "writer": "Jean Guitton, Jean Laviron",
  "actors": "Henri Génès, Liliane Bert, Julien Carette",
  "plot": "Mr. Pierre Montabrel has spent all the night with his mistress.On the morning Gisèle Montabrel, his wife, is preoccupied because Pierre is not at home.Then arrives Jacques Lambert, the associate of Pierre, Gisèle asks him if he ha...",
  "language": "French",
  "country": "France",
  "awards": "N/A",
  "poster": "https://m.media-amazon.com/images/M/MV5BNWNlNzgwYTMtNjE2MC00MDUyLWI0NGMtNjRjMTY2NDdjNTRlXkEyXkFqcGc@._V1_SX300.jpg",
  "ratings": [
    {
      "Source": "Internet Movie Database",
      "Value": "5.0/10"
    }
  ],
  "metascore": "N/A",
  "imdbRating": "5.0",
  "imdbID": "tt0044383",
  "type": "movie",
  "fetched_at": "2026-05-15T21:16:14.661Z"
}