{
  "title": "Un'alba",
  "year": "1920",
  "rated": "N/A",
  "released": "01 Nov 1920",
  "runtime": "N/A",
  "genre": "N/A",
  "director": "Eugenio Fontana",
  "writer": "V.I. Lenin (play)",
  "actors": "Nada De Wincy, Egea, Guido Guiducci, Fosco Risturi",
  "plot": "N/A",
  "language": "Italian",
  "country": "Italy",
  "awards": "N/A",
  "poster": "N/A",
  "ratings": [],
  "metascore": "N/A",
  "imdbRating": "N/A",
  "imdbID": "tt1184682",
  "type": "movie",
  "fetched_at": "2026-03-10T13:16:32.068Z"
}