{
  "title": "Vendetta",
  "year": "1950",
  "rated": "PG",
  "released": "01 Jun 1951",
  "runtime": "83 min",
  "genre": "Crime, Drama",
  "director": "Mel Ferrer, Stuart Heisler, Max Ophüls",
  "writer": "W.R. Burnett, Prosper Mérimée, Peter O'Crotty",
  "actors": "Faith Domergue, George Dolenz, Donald Buka",
  "plot": "The daughter of a slain man pushes her brother toward vengeance in 19th-century Corsica.",
  "language": "Italian, English",
  "country": "United States",
  "awards": "N/A",
  "poster": "https://m.media-amazon.com/images/M/MV5BNWY4N2Y4NGUtNjk1Yy00Zjc0LWI5NDEtNGZkYjkyMjgyOGUyXkEyXkFqcGdeQXVyNDMzNDQ4ODA@._V1_SX300.jpg",
  "ratings": [
    {
      "Source": "Internet Movie Database",
      "Value": "6.0/10"
    }
  ],
  "metascore": "N/A",
  "imdbRating": "6.0",
  "imdbID": "tt0043100",
  "type": "movie",
  "fetched_at": "2026-05-06T02:26:54.545Z"
}