{
  "title": "We Bury the Dead",
  "year": "2024",
  "rated": "N/A",
  "released": "01 Nov 2024",
  "runtime": "N/A",
  "genre": "Horror, Thriller",
  "director": "Zak Hilditch",
  "writer": "Zak Hilditch",
  "actors": "Daisy Ridley, Brenton Thwaites, Matt Whelan",
  "plot": "Ava, a desperate woman whose husband is missing in the aftermath of a catastrophic military experiment, joins a \"body retrieval unit,\" but her search takes a chilling turn when the corpses she's burying start showing signs of life.",
  "language": "English",
  "country": "Australia",
  "awards": "N/A",
  "poster": "https://m.media-amazon.com/images/M/MV5BZTM0MWUzNjMtNjViNS00MWE5LWIwNWYtYTk1Nzg4OWJlNGI4XkEyXkFqcGc@._V1_SX300.jpg",
  "ratings": [
    {
      "Source": "Rotten Tomatoes",
      "Value": "92%"
    }
  ],
  "metascore": "N/A",
  "imdbRating": "N/A",
  "imdbID": "tt29713093",
  "type": "movie",
  "fetched_at": "2026-02-11T19:16:48.372Z"
}
