{
  "title": "Without Benefit of Clergy",
  "year": "1921",
  "rated": "N/A",
  "released": "19 Jun 1921",
  "runtime": "60 min",
  "genre": "Drama",
  "director": "James Young",
  "writer": "Rudyard Kipling, Randolph Lewis",
  "actors": "Virginia Brown Faire, Thomas Holding, Evelyn Selbie",
  "plot": "A British engineer in India takes a simple native girl as his bride, an act which defies social strictures and leads to tragedy.",
  "language": "None, English",
  "country": "United States",
  "awards": "N/A",
  "poster": "https://m.media-amazon.com/images/M/MV5BYWZlYjJjOTAtNTI2Ni00MWVmLWE3OWQtY2JlOTI3NGQwMTBhXkEyXkFqcGdeQXVyNjA5MTAzODY@._V1_SX300.jpg",
  "ratings": [
    {
      "Source": "Internet Movie Database",
      "Value": "5.2/10"
    }
  ],
  "metascore": "N/A",
  "imdbRating": "5.2",
  "imdbID": "tt0012856",
  "type": "movie",
  "fetched_at": "2026-03-10T13:19:35.069Z"
}