{
  "isbn": null,
  "upc": "596060699800411",
  "title": "Dark X-Men #4",
  "authors": [
    "Alan Fine",
    "Brian Reber",
    "Dan Buckley",
    "Daniel Ketchum",
    "Joe Quesada",
    "Leonard Kirk",
    "Mike Choi",
    "Nick Lowe",
    "Paul Cornell",
    "Rob Steen",
    "Sonia Oback",
    "Taylor Esposito"
  ],
  "publish_date": "2010-02-10",
  "publisher": [
    "Marvel"
  ],
  "pages": 0,
  "cover": "https://static.metron.cloud/media/issue/2021/03/22/dark-x-men-4.jpg",
  "subjects": [],
  "url": "https://metron.cloud/issue/27735/",
  "fetched_at": "2026-04-23T19:06:05.933Z",
  "reviewed_at": null
}