{
  "isbn": null,
  "upc": "725130181787",
  "title": "Flash Gordon: Zeitgeist #1",
  "authors": [
    "Alex Ross",
    "Daniel Indro",
    "Eric Trautmann",
    "Francesco Francavilla",
    "Paul Renaud",
    "Simon Bowland",
    "Slamet Mujiono",
    "Wagner Reis"
  ],
  "publish_date": "2011-11-30",
  "publisher": [
    "Dynamite Entertainment"
  ],
  "pages": 0,
  "cover": "https://static.metron.cloud/media/issue/2025/03/03/554571d65efb4300aa259f0670bd5acc.jpg",
  "subjects": [],
  "url": "https://metron.cloud/issue/137347/",
  "fetched_at": "2026-06-07T19:44:22.164Z",
  "reviewed_at": null
}