{
  "isbn": null,
  "upc": "75960608602300911",
  "title": "Amazing Spider-Man: Renew Your Vows #9",
  "authors": [
    "Alan Fine",
    "Allison Stock",
    "Axel Alonso",
    "Dan Buckley",
    "Darren Shan",
    "Gerry Conway",
    "Jesus Aburtov",
    "Joe Caramagna",
    "Joe Quesada",
    "Juan Frigeri",
    "Ryan Stegman"
  ],
  "publish_date": "2017-07-19",
  "publisher": [
    "Marvel"
  ],
  "pages": 0,
  "cover": "https://static.metron.cloud/media/issue/2021/06/27/amazing-spider-man-renew-your-vows-v2-9.jpg",
  "subjects": [],
  "url": "https://metron.cloud/issue/33164/",
  "fetched_at": "2026-05-28T14:19:51.259Z",
  "reviewed_at": null
}