{
  "isbn": null,
  "upc": "76194132437101211",
  "title": "Deathstroke #12",
  "authors": [
    "Arif Prianto",
    "Dave Sharpe",
    "Eddie Berganza",
    "James Bonny",
    "Paul Kaminski",
    "Ryan Benjamin",
    "Spike Brandt",
    "Tomeu Morey",
    "Tony Daniel",
    "Tyler Kirkham"
  ],
  "publish_date": "2015-11-25",
  "publisher": [
    "DC Comics"
  ],
  "pages": 0,
  "cover": "https://static.metron.cloud/media/issue/2023/02/21/5e9dfbfb0144444ba608d02ef35c540c.jpg",
  "subjects": [],
  "url": "https://metron.cloud/issue/56812/",
  "fetched_at": "2026-03-10T13:18:09.239Z"
}