{
  "isbn": null,
  "upc": "76194134177403811",
  "title": "Batman Beyond #38",
  "authors": [
    "Chris Sotomayor",
    "Dan Jurgens",
    "Elizabeth Breitweiser",
    "Francis Manapul",
    "Jamie S. Rich",
    "Jessica Chen",
    "Lee Weeks",
    "Rob Levin",
    "Sean Chen",
    "Sean Parsons",
    "Travis Lanham"
  ],
  "publish_date": "2019-11-27",
  "publisher": [
    "DC Comics"
  ],
  "pages": 0,
  "cover": "https://static.metron.cloud/media/issue/2021/09/18/batman-beyond-38.jpg",
  "subjects": [],
  "url": "https://metron.cloud/issue/38350/",
  "fetched_at": "2026-04-22T14:12:38.363Z"
}