{
  "isbn": null,
  "upc": "76194122208000611",
  "title": "Batman / Huntress: Cry for Blood #6",
  "authors": [
    "Clem Robins",
    "Dennis O'Neil",
    "Greg Rucka",
    "Joseph Illidge",
    "Rick Burchett",
    "Tatjana Wood",
    "Terry Beatty"
  ],
  "publish_date": "2000-09-13",
  "publisher": [
    "DC Comics"
  ],
  "pages": 0,
  "cover": "https://static.metron.cloud/media/issue/2019/03/01/Batman-Huntress-Cry-6.jpg",
  "subjects": [],
  "url": "https://metron.cloud/issue/1411/",
  "fetched_at": "2026-05-06T22:58:24.622Z",
  "reviewed_at": null
}