{
  "isbn": null,
  "upc": "76194120477205711",
  "title": "Animaniacs #57",
  "authors": [
    "Bob LeRose",
    "Debbie Sternecky",
    "Harvey Richards",
    "Heidi MacDonald",
    "Horacio Ottolini",
    "Jennifer Keating Moore",
    "Jesse Leon McCann",
    "Jim Amash",
    "John Costanza",
    "Leo Batic",
    "Matt Wayne",
    "Neal Sternecky",
    "Phil Hugh Felix",
    "Sean Carolan",
    "Todd Klein",
    "Walter Carzon"
  ],
  "publish_date": "2000-02-01",
  "publisher": [
    "DC Comics"
  ],
  "pages": 0,
  "cover": "https://static.metron.cloud/media/issue/2025/09/22/970767d8d4864c9f8ccf127fe26661e0.jpg",
  "subjects": [],
  "url": "https://metron.cloud/issue/155136/",
  "fetched_at": "2026-04-21T16:32:55.485Z"
}