{
  "isbn": null,
  "upc": "76194130640701511",
  "title": "Batman #15",
  "authors": [
    "David Baron",
    "FCO Plascencia",
    "Greg Capullo",
    "James Tynion IV",
    "Jimmy Betancourt",
    "Jock",
    "Jonathan Glapion",
    "Katie Kubert",
    "Mike Marts",
    "Richard Starkings",
    "Scott Snyder",
    "Taylor Esposito"
  ],
  "publish_date": "2012-12-12",
  "publisher": [
    "DC Comics"
  ],
  "pages": 0,
  "cover": "https://static.metron.cloud/media/issue/2019/10/22/batman-v2-15.jpg",
  "subjects": [],
  "url": "https://metron.cloud/issue/6812/",
  "fetched_at": "2026-05-15T21:22:53.971Z",
  "reviewed_at": null
}