{
  "isbn": null,
  "upc": "76194130502801011",
  "title": "Deathstroke #10",
  "authors": [
    "Andy Troy",
    "Brian Smith",
    "Jacob Bear",
    "Rob Liefeld",
    "Ross Hughes",
    "Travis Lanham"
  ],
  "publish_date": "2012-06-13",
  "publisher": [
    "DC Comics"
  ],
  "pages": 0,
  "cover": "https://static.metron.cloud/media/issue/2023/02/21/3cad2b05eef0440a8977d59a84b83a1f.jpeg",
  "subjects": [],
  "url": "https://metron.cloud/issue/56789/",
  "fetched_at": "2026-03-10T13:16:36.728Z"
}