{
  "isbn": null,
  "upc": "76194134014200111",
  "title": "Aquaman: Rebirth #1",
  "authors": [
    "Amedeo Turturro",
    "Andrew Hennessy",
    "Brad Walker",
    "Brian Cunningham",
    "Dan Abnett",
    "Gabe Eltaeb",
    "Mark Morales",
    "Oscar Jiménez",
    "Pat Brosseau",
    "Scot Eaton"
  ],
  "publish_date": "2016-06-08",
  "publisher": [
    "DC Comics"
  ],
  "pages": 0,
  "cover": "https://static.metron.cloud/media/issue/2019/06/20/aquaman-rebirth-1.jpg",
  "subjects": [],
  "url": "https://metron.cloud/issue/2907/",
  "fetched_at": "2026-06-02T16:55:17.700Z",
  "reviewed_at": null
}