{
  "isbn": null,
  "upc": "76194138066700611",
  "title": "Jay Garrick: The Flash #6",
  "authors": [
    "Andrew Marino",
    "Diego Olortegui",
    "Francis Manapul",
    "Jeremy Adams",
    "Jim Lee",
    "Jorge Corona",
    "Katie Kubert",
    "Luis Guerrero",
    "Marie Javins",
    "Marquis Draper",
    "Sarah Stern",
    "Steve Wands"
  ],
  "publish_date": "2024-04-16",
  "publisher": [
    "DC Comics"
  ],
  "pages": 0,
  "cover": "https://static.metron.cloud/media/issue/2024/03/29/07d55bc721f44dd1acdbebb0f06136f0.jpg",
  "subjects": [],
  "url": "https://metron.cloud/issue/115241/",
  "fetched_at": "2026-06-07T20:17:41.545Z",
  "reviewed_at": null
}